whine/__init__.py
whine/event_handler.py
whine-0.1.0.dist-info/METADATA
whine-0.1.0.dist-info/WHEEL
whine-0.1.0.dist-info/top_level.txt
whine-0.1.0.dist-info/zip-safe
whine-0.1.0.dist-info/RECORD
