Metadata-Version: 2.1
Name: whine
Version: 0.1.0
Summary: Lightweight notification package for custom subscribe-dispatch events
Home-page: https://github.com/den4uk/whine
Author: Denis Sazonov
Author-email: den@saz.lt
License: "MIT License"
Project-URL: Source Code, https://github.com/den4uk/whine
Keywords: whine events dispatch
Classifier: Development Status :: 4 - Beta
Classifier: Programming Language :: Python :: 3
Classifier: Programming Language :: Python :: 3.8
Classifier: Programming Language :: Python :: 3.9
Classifier: Programming Language :: Python :: 3.10
Classifier: Operating System :: OS Independent
Classifier: License :: OSI Approved :: MIT License
Classifier: Intended Audience :: Developers
Classifier: Topic :: Utilities
Classifier: Topic :: Software Development :: Libraries
Requires-Python: >=3.8
